LICENSE
README.md
setup.py
ToDo_Task_Manager_Tool.egg-info/PKG-INFO
ToDo_Task_Manager_Tool.egg-info/SOURCES.txt
ToDo_Task_Manager_Tool.egg-info/dependency_links.txt
ToDo_Task_Manager_Tool.egg-info/entry_points.txt
ToDo_Task_Manager_Tool.egg-info/requires.txt
ToDo_Task_Manager_Tool.egg-info/top_level.txt
ToDo_Task_manager_Tool.egg-info/PKG-INFO
ToDo_Task_manager_Tool.egg-info/SOURCES.txt
ToDo_Task_manager_Tool.egg-info/dependency_links.txt
ToDo_Task_manager_Tool.egg-info/entry_points.txt
ToDo_Task_manager_Tool.egg-info/requires.txt
ToDo_Task_manager_Tool.egg-info/top_level.txt
todo/__init__.py
todo/database.py
todo/task.py