Metadata-Version: 2.1
Name: ToDo-Task-Manager-Tool
Version: 0.1.0
Summary: Todo manager tool
Home-page: https://github.com/kasul092/todo
Author: Sumit Pujari
Author-email: sumitpujari199723@gmail.com
License: UNKNOWN
Platform: UNKNOWN
Requires-Python: >=3.6
